README.md
setup.py
gributils/__init__.py
gributils/bounds.py
gributils/cli.py
gributils/gribindex.py
gributils/layer.py
gributils/projection.py
gributils/server.py
gributils/uv.py
gributils.egg-info/PKG-INFO
gributils.egg-info/SOURCES.txt
gributils.egg-info/dependency_links.txt
gributils.egg-info/entry_points.txt
gributils.egg-info/requires.txt
gributils.egg-info/top_level.txt