Metadata-Version: 2.1
Name: gributils
Version: 0.10
Summary: Utils on top of pygrib for extracting metadata and manipulating grib files
Home-page: https://github.com/innovationgarage/gributils
Author: Egil Moeller
Author-email: egil@innovationgarage.no
License: UNKNOWN
Platform: UNKNOWN
